{"cameraMode":{"drawMode":0,"name":"Shaded","section":"Shading Mode"},"sceneLighting":true,"audioPlay":false,"sceneViewState":{"showFog":true,"showMaterialUpdate":false,"showSkybox":true,"showFlares":true,"showImageEffects":true,"showParticleSystems":true},"in2DMode":false,"pivot":{"x":0.15312257409095765,"y":-2.0013744831085207,"z":0.07633614540100098},"rotation":{"x":-0.6085949540138245,"y":-0.006668173708021641,"z":0.00511515187099576,"w":-0.7934479713439941},"size":7.041077136993408,"orthographic":false}